odoo/addons/project_parent_task_filter/README.rst
odoo/addons/project_parent_task_filter/__init__.py
odoo/addons/project_parent_task_filter/__manifest__.py
odoo/addons/project_parent_task_filter/i18n/ca.po
odoo/addons/project_parent_task_filter/i18n/de.po
odoo/addons/project_parent_task_filter/i18n/es.po
odoo/addons/project_parent_task_filter/i18n/es_AR.po
odoo/addons/project_parent_task_filter/i18n/es_ES.po
odoo/addons/project_parent_task_filter/i18n/fr.po
odoo/addons/project_parent_task_filter/i18n/fr_FR.po
odoo/addons/project_parent_task_filter/i18n/it.po
odoo/addons/project_parent_task_filter/i18n/nl_NL.po
odoo/addons/project_parent_task_filter/i18n/project_parent_task_filter.pot
odoo/addons/project_parent_task_filter/i18n/pt_BR.po
odoo/addons/project_parent_task_filter/readme/CONTRIBUTORS.md
odoo/addons/project_parent_task_filter/readme/DESCRIPTION.md
odoo/addons/project_parent_task_filter/readme/ROADMAP.md
odoo/addons/project_parent_task_filter/readme/USAGE.md
odoo/addons/project_parent_task_filter/static/description/icon.png
odoo/addons/project_parent_task_filter/static/description/index.html
odoo/addons/project_parent_task_filter/views/project_task.xml
odoo_addon_project_parent_task_filter-18.0.1.0.0.2.dist-info/METADATA
odoo_addon_project_parent_task_filter-18.0.1.0.0.2.dist-info/WHEEL
odoo_addon_project_parent_task_filter-18.0.1.0.0.2.dist-info/top_level.txt
odoo_addon_project_parent_task_filter-18.0.1.0.0.2.dist-info/RECORD
